ManagerCSV/__init__.py
ManagerCSV/index.py
ManagerCSV-1.0.1.dist-info/LICENSE
ManagerCSV-1.0.1.dist-info/METADATA
ManagerCSV-1.0.1.dist-info/WHEEL
ManagerCSV-1.0.1.dist-info/top_level.txt
ManagerCSV-1.0.1.dist-info/RECORD
