Metadata-Version: 2.1
Name: ManagerCSV
Version: 1.0.1
Summary: Just a random package to deal with CSV files 
Author-email: Dulinniel <nightingalenervous@gmail.com>
Project-URL: Homepage, https://github.com/Dulinniel/CSVManager/tree/main
Project-URL: Bug Tracker, https://github.com/Dulinniel/CSVManager/issues
Classifier: Programming Language :: Python :: 3
Classifier: License :: OSI Approved :: MIT License
Classifier: Operating System :: OS Independent
Requires-Python: >=3.10.7
License-File: LICENSE
